CHANGES.txt
MANIFEST.in
README.txt
TODO.txt
setup.py
sdistmaker/USAGE.txt
sdistmaker/__init__.py
sdistmaker/cornercases.txt
sdistmaker/defaults.py
sdistmaker/find_tarball.txt
sdistmaker/iterator.py
sdistmaker/maker.py
sdistmaker.egg-info/PKG-INFO
sdistmaker.egg-info/SOURCES.txt
sdistmaker.egg-info/dependency_links.txt
sdistmaker.egg-info/entry_points.txt
sdistmaker.egg-info/not-zip-safe
sdistmaker.egg-info/requires.txt
sdistmaker.egg-info/top_level.txt
sdistmaker/tests/__init__.py
sdistmaker/tests/sample.txt
sdistmaker/tests/test_setup.py