Metadata-Version: 1.0
Name: sdistmaker
Version: 1.4
Summary: Make sdists tarballs for projects in svn tree
Home-page: http://bitbucket.org/reinout/sdistmaker/
Author: Reinout van Rees
Author-email: reinout@vanrees.org
License: BSD
Platform: UNKNOWN
